sentry_slack/__init__.py
sentry_slack/models.py
sentry_slack/plugin.py
sentry_slack-0.5.0.dist-info/DESCRIPTION.rst
sentry_slack-0.5.0.dist-info/entry_points.txt
sentry_slack-0.5.0.dist-info/METADATA
sentry_slack-0.5.0.dist-info/metadata.json
sentry_slack-0.5.0.dist-info/pbr.json
sentry_slack-0.5.0.dist-info/RECORD
sentry_slack-0.5.0.dist-info/top_level.txt
sentry_slack-0.5.0.dist-info/WHEEL
