Metadata-Version: 2.0
Name: sentry-slack
Version: 0.5.0
Summary: A Sentry extension which posts notifications to Slack (https://slack.com/).
Home-page: https://github.com/getsentry/sentry-slack
Author: Matt Robenolt
Author-email: matt@ydekproductons.com
License: BSD
Platform: UNKNOWN
Classifier: Framework :: Django
Classifier: Intended Audience :: Developers
Classifier: Intended Audience :: System Administrators
Classifier: Operating System :: OS Independent
Classifier: Topic :: Software Development
Requires-Dist: sentry (>=7.0.0)
Provides-Extra: tests
Requires-Dist: exam; extra == 'tests'
Requires-Dist: flake8 (>=2.0,<2.1); extra == 'tests'
Requires-Dist: responses; extra == 'tests'
